duckduckgo_mcp_server/__init__.py
duckduckgo_mcp_server/main.py
ddg_mcp_server-0.1.1.dist-info/LICENSE
ddg_mcp_server-0.1.1.dist-info/METADATA
ddg_mcp_server-0.1.1.dist-info/WHEEL
ddg_mcp_server-0.1.1.dist-info/entry_points.txt
ddg_mcp_server-0.1.1.dist-info/top_level.txt
ddg_mcp_server-0.1.1.dist-info/RECORD
