Metadata-Version: 2.2
Name: ddg-mcp-server
Version: 0.1.1
Summary: DuckDuckGo MCP Server
Project-URL: Homepage, https://github.com/AshDevFr/duckduckgo-mcp-server
Project-URL: Issues, https://github.com/AshDevFr/duckduckgo-mcp-server/issues
Requires-Python: <3.13,>=3.12
License-File: LICENSE
Requires-Dist: duckduckgo-search>=7.5.1
Requires-Dist: httpx>=0.28.1
Requires-Dist: mcp[cli]>=1.3.0
